{
  "folder": "EahEqRL4FYwBaOIR",
  "name": "Apply 'In a Bad Spot'",
  "type": "script",
  "_id": "yIybyXEeqYCwy9xe",
  "author": "MmM06BuCrG9h1GLg",
  "img": "icons/svg/dice-target.svg",
  "scope": "global",
  "command": "if (!canvas.tokens.controlled.length) {\n    ui.notifications.warn(\"Please select at least one token.\");\n    return;\n}\n\nconst statusDesired = \"inABadSpot\";\n\nfor (let token of canvas.tokens.controlled) {\n    const actor = token.actor;\n        const data = {\n            system: {\n                combatPosition: statusDesired,\n            },\n        };\n        await actor.update(data);\n}",
  "sort": 0,
  "ownership": {
    "default": 0,
    "MmM06BuCrG9h1GLg": 3
  },
  "flags": {},
  "_stats": {
    "compendiumSource": null,
    "duplicateSource": null,
    "exportSource": null,
    "coreVersion": "13.351",
    "systemId": "foundry-ironsworn",
    "systemVersion": "1.27.0",
    "createdTime": 1777350294001,
    "modifiedTime": 1777350294001,
    "lastModifiedBy": "MmM06BuCrG9h1GLg"
  },
  "_key": "!macros!yIybyXEeqYCwy9xe"
}
